adnotatio_server/__init__.py
adnotatio_server/__main__.py
adnotatio_server/_version.py
adnotatio_server/auth.py
adnotatio_server/blueprint.py
adnotatio_server/jsonapi.py
adnotatio_server/v2.py
adnotatio_server/storage/__init__.py
adnotatio_server/storage/database.py
adnotatio_server/storage/models.py
adnotatio_server/storage/util.py
adnotatio_server-0.0.2.dist-info/LICENSE
adnotatio_server-0.0.2.dist-info/METADATA
adnotatio_server-0.0.2.dist-info/WHEEL
adnotatio_server-0.0.2.dist-info/top_level.txt
adnotatio_server-0.0.2.dist-info/RECORD
